[
  {
    "location": {
      "name": "Algeria"
    },
    "children": [
      {
        "location": {
          "name": "Algiers"
        }
      },
      {
        "location": {
          "name": "Annaba"
        }
      },
      {
        "location": {
          "name": "Azazga"
        }
      },
      {
        "location": {
          "name": "Batna City"
        }
      },
      {
        "location": {
          "name": "Blida"
        }
      },
      {
        "location": {
          "name": "Bordj"
        }
      },
      {
        "location": {
          "name": "Bordj Bou Arreridj"
        }
      },
      {
        "location": {
          "name": "Bougara"
        }
      },
      {
        "location": {
          "name": "Cheraga"
        }
      },
      {
        "location": {
          "name": "Chlef"
        }
      },
      {
        "location": {
          "name": "Constantine"
        }
      },
      {
        "location": {
          "name": "Djelfa"
        }
      },
      {
        "location": {
          "name": "Draria"
        }
      },
      {
        "location": {
          "name": "El Tarf"
        }
      },
      {
        "location": {
          "name": "Hussein Dey"
        }
      },
      {
        "location": {
          "name": "Illizi"
        }
      },
      {
        "location": {
          "name": "Jijel"
        }
      },
      {
        "location": {
          "name": "Kouba"
        }
      },
      {
        "location": {
          "name": "Laghouat"
        }
      },
      {
        "location": {
          "name": "Oran"
        }
      },
      {
        "location": {
          "name": "Ouargla"
        }
      },
      {
        "location": {
          "name": "Oued Smar"
        }
      },
      {
        "location": {
          "name": "Relizane"
        }
      },
      {
        "location": {
          "name": "Rouiba"
        }
      },
      {
        "location": {
          "name": "Saida"
        }
      },
      {
        "location": {
          "name": "Souk Ahras"
        }
      },
      {
        "location": {
          "name": "Tamanghasset"
        }
      },
      {
        "location": {
          "name": "Tiaret"
        }
      },
      {
        "location": {
          "name": "Tissemsilt"
        }
      },
      {
        "location": {
          "name": "Tizi"
        }
      },
      {
        "location": {
          "name": "Tizi Ouzou"
        }
      },
      {
        "location": {
          "name": "Tlemcen"
        }
      }
    ]
  },
  {
    "location": {
      "name": "Angola"
    },
    "children": [
      {
        "location": {
          "name": "Ambriz"
        }
      },
      {
        "location": {
          "name": "Benguela"
        }
      },
      {
        "location": {
          "name": "Cabinda"
        }
      },
      {
        "location": {
          "name": "Cacole"
        }
      },
      {
        "location": {
          "name": "Camabatela"
        }
      },
      {
        "location": {
          "name": "Cazeta"
        }
      },
      {
        "location": {
          "name": "Huambo"
        }
      },
      {
        "location": {
          "name": "Kuito"
        }
      },
      {
        "location": {
          "name": "Lobito"
        }
      },
      {
        "location": {
          "name": "Luanda"
        }
      },
      {
        "location": {
          "name": "Lubango"
        }
      },
      {
        "location": {
          "name": "Lucapa"
        }
      },
      {
        "location": {
          "name": "Lumeje"
        }
      },
      {
        "location": {
          "name": "Malanje"
        }
      },
      {
        "location": {
          "name": "Menongue"
        }
      },
      {
        "location": {
          "name": "Muxaluando"
        }
      },
      {
        "location": {
          "name": "Namibe"
        }
      },
      {
        "location": {
          "name": "Ondjiva"
        }
      },
      {
        "location": {
          "name": "Piri"
        }
      },
      {
        "location": {
          "name": "Saurimo"
        }
      },
      {
        "location": {
          "name": "Talatona"
        }
      }
    ]
  },
  {
    "location": {
      "name": "Botswana"
    },
    "children": [
      {
        "location": {
          "name": "Francistown"
        }
      },
      {
        "location": {
          "name": "Gaborone"
        }
      },
      {
        "location": {
          "name": "Orapa"
        }
      },
      {
        "location": {
          "name": "Serowe"
        }
      },
      {
        "location": {
          "name": "Village"
        }
      }
    ]
  },
  {
    "location": {
      "name": "Cameroon"
    },
    "children": [
      {
        "location": {
          "name": "Bafia"
        }
      },
      {
        "location": {
          "name": "Bafoussam"
        }
      },
      {
        "location": {
          "name": "Bamenda"
        }
      },
      {
        "location": {
          "name": "Buea"
        }
      },
      {
        "location": {
          "name": "Douala"
        }
      },
      {
        "location": {
          "name": "Kribi"
        }
      },
      {
        "location": {
          "name": "Kumba"
        }
      },
      {
        "location": {
          "name": "Ringo"
        }
      },
      {
        "location": {
          "name": "Tibati"
        }
      }
    ]
  },
  {
    "location": {
      "name": "Congo"
    },
    "children": [
      {
        "location": {
          "name": "Banana"
        }
      },
      {
        "location": {
          "name": "Goma"
        }
      },
      {
        "location": {
          "name": "Kinshasa"
        }
      },
      {
        "location": {
          "name": "Likasi"
        }
      },
      {
        "location": {
          "name": "Lubumbashi"
        }
      }
    ]
  },
  {
    "location": {
      "name": "Egypt"
    },
    "children": [
      {
        "location": {
          "name": "Abu Hammad"
        }
      },
      {
        "location": {
          "name": "Al Mahallah al Kubra"
        }
      },
      {
        "location": {
          "name": "Al Mansurah"
        }
      },
      {
        "location": {
          "name": "Al Marj"
        }
      },
      {
        "location": {
          "name": "Alexandria"
        }
      },
      {
        "location": {
          "name": "Almazah"
        }
      },
      {
        "location": {
          "name": "Ar Rawdah"
        }
      },
      {
        "location": {
          "name": "Assiut"
        }
      },
      {
        "location": {
          "name": "Az Zamalik"
        }
      },
      {
        "location": {
          "name": "Badr"
        }
      },
      {
        "location": {
          "name": "Banha"
        }
      },
      {
        "location": {
          "name": "Bani Suwayf"
        }
      },
      {
        "location": {
          "name": "Cairo"
        }
      },
      {
        "location": {
          "name": "Damietta"
        }
      },
      {
        "location": {
          "name": "Faraskur"
        }
      },
      {
        "location": {
          "name": "Flaminj"
        }
      },
      {
        "location": {
          "name": "Giza"
        }
      },
      {
        "location": {
          "name": "Heliopolis"
        }
      },
      {
        "location": {
          "name": "Helwan"
        }
      },
      {
        "location": {
          "name": "Hurghada"
        }
      },
      {
        "location": {
          "name": "Ismailia"
        }
      },
      {
        "location": {
          "name": "Kafr ash Shaykh"
        }
      },
      {
        "location": {
          "name": "Luxor"
        }
      },
      {
        "location": {
          "name": "Madinat an Nasr"
        }
      },
      {
        "location": {
          "name": "Madinat as Sadis min Uktubar"
        }
      },
      {
        "location": {
          "name": "Minya"
        }
      },
      {
        "location": {
          "name": "Nasr"
        }
      },
      {
        "location": {
          "name": "New Cairo"
        }
      },
      {
        "location": {
          "name": "Port Said"
        }
      },
      {
        "location": {
          "name": "Rafah"
        }
      },
      {
        "location": {
          "name": "Ramsis"
        }
      },
      {
        "location": {
          "name": "Sadat"
        }
      },
      {
        "location": {
          "name": "Shirbin"
        }
      },
      {
        "location": {
          "name": "Shubra"
        }
      },
      {
        "location": {
          "name": "Sohag"
        }
      },
      {
        "location": {
          "name": "Suez"
        }
      },
      {
        "location": {
          "name": "Tanta"
        }
      },
      {
        "location": {
          "name": "Toukh"
        }
      },
      {
        "location": {
          "name": "Zagazig"
        }
      }
    ]
  },
  {
    "location": {
      "name": "Gabon"
    },
    "children": [
      {
        "location": {
          "name": "Gamba"
        }
      },
      {
        "location": {
          "name": "Libreville"
        }
      },
      {
        "location": {
          "name": "Mamagnia"
        }
      },
      {
        "location": {
          "name": "Moanda"
        }
      },
      {
        "location": {
          "name": "Port-Gentil"
        }
      }
    ]
  },
  {
    "location": {
      "name": "Georgia"
    },
    "children": [
      {
        "location": {
          "name": "Gogolesubani"
        }
      },
      {
        "location": {
          "name": "Kutaisi"
        }
      },
      {
        "location": {
          "name": "Lentekhi"
        }
      },
      {
        "location": {
          "name": "Qazbegi"
        }
      },
      {
        "location": {
          "name": "Samtredia"
        }
      },
      {
        "location": {
          "name": "Sukhumi"
        }
      },
      {
        "location": {
          "name": "Tbilisi"
        }
      },
      {
        "location": {
          "name": "Zemo-Avchala"
        }
      },
      {
        "location": {
          "name": "Zugdidi"
        }
      }
    ]
  },
  {
    "location": {
      "name": "Ghana"
    },
    "children": [
      {
        "location": {
          "name": "Accra"
        }
      },
      {
        "location": {
          "name": "Bawku"
        }
      },
      {
        "location": {
          "name": "Berekum"
        }
      },
      {
        "location": {
          "name": "Bolgatanga"
        }
      },
      {
        "location": {
          "name": "Cape Coast"
        }
      },
      {
        "location": {
          "name": "Home"
        }
      },
      {
        "location": {
          "name": "Koforidua"
        }
      },
      {
        "location": {
          "name": "Kumasi"
        }
      },
      {
        "location": {
          "name": "Legon"
        }
      },
      {
        "location": {
          "name": "Mampong"
        }
      },
      {
        "location": {
          "name": "Navrongo"
        }
      },
      {
        "location": {
          "name": "Sunyani"
        }
      },
      {
        "location": {
          "name": "Takoradi"
        }
      },
      {
        "location": {
          "name": "Tema"
        }
      },
      {
        "location": {
          "name": "Wa"
        }
      },
      {
        "location": {
          "name": "Winneba"
        }
      }
    ]
  },
  {
    "location": {
      "name": "Guinea"
    },
    "children": [
      {
        "location": {
          "name": "Conakry"
        }
      },
      {
        "location": {
          "name": "Dabola"
        }
      },
      {
        "location": {
          "name": "Kalia"
        }
      },
      {
        "location": {
          "name": "Kankan"
        }
      },
      {
        "location": {
          "name": "Lola"
        }
      },
      {
        "location": {
          "name": "Mamou"
        }
      },
      {
        "location": {
          "name": "Port Kamsar"
        }
      },
      {
        "location": {
          "name": "Sangaredi"
        }
      }
    ]
  },
  {
    "location": {
      "name": "Kenya"
    },
    "children": [
      {
        "location": {
          "name": "Bondo"
        }
      },
      {
        "location": {
          "name": "Chuka"
        }
      },
      {
        "location": {
          "name": "Eldoret"
        }
      },
      {
        "location": {
          "name": "Kabete"
        }
      },
      {
        "location": {
          "name": "Kaiboi"
        }
      },
      {
        "location": {
          "name": "Karatina"
        }
      },
      {
        "location": {
          "name": "Kiambu"
        }
      },
      {
        "location": {
          "name": "Kikuyu"
        }
      },
      {
        "location": {
          "name": "Kisii"
        }
      },
      {
        "location": {
          "name": "Kisumu"
        }
      },
      {
        "location": {
          "name": "Kitale"
        }
      },
      {
        "location": {
          "name": "Kitui"
        }
      },
      {
        "location": {
          "name": "Machakos"
        }
      },
      {
        "location": {
          "name": "Maseno"
        }
      },
      {
        "location": {
          "name": "Mbita"
        }
      },
      {
        "location": {
          "name": "Mombasa"
        }
      },
      {
        "location": {
          "name": "Nairobi"
        }
      },
      {
        "location": {
          "name": "Nakuru"
        }
      },
      {
        "location": {
          "name": "Sawa Sawa"
        }
      },
      {
        "location": {
          "name": "Siaya"
        }
      },
      {
        "location": {
          "name": "Thika"
        }
      },
      {
        "location": {
          "name": "Turbo"
        }
      },
      {
        "location": {
          "name": "Wote"
        }
      }
    ]
  },
  {
    "location": {
      "name": "Libya"
    },
    "children": [
      {
        "location": {
          "name": "Benghazi"
        }
      },
      {
        "location": {
          "name": "Misratah"
        }
      },
      {
        "location": {
          "name": "Sabha"
        }
      },
      {
        "location": {
          "name": "Tripoli"
        }
      },
      {
        "location": {
          "name": "Zliten"
        }
      }
    ]
  },
  {
    "location": {
      "name": "Madagascar"
    },
    "children": [
      {
        "location": {
          "name": "Ambanja"
        }
      },
      {
        "location": {
          "name": "Antananarivo"
        }
      },
      {
        "location": {
          "name": "Antsirabe"
        }
      },
      {
        "location": {
          "name": "Antsiranana"
        }
      },
      {
        "location": {
          "name": "Fianarantsoa"
        }
      },
      {
        "location": {
          "name": "Toamasina"
        }
      },
      {
        "location": {
          "name": "Toliara"
        }
      }
    ]
  },
  {
    "location": {
      "name": "Morocco"
    },
    "children": [
      {
        "location": {
          "name": "Afourer"
        }
      },
      {
        "location": {
          "name": "Agadir"
        }
      },
      {
        "location": {
          "name": "Ait Melloul"
        }
      },
      {
        "location": {
          "name": "Al Hoceima"
        }
      },
      {
        "location": {
          "name": "Assa"
        }
      },
      {
        "location": {
          "name": "Benguerir"
        }
      },
      {
        "location": {
          "name": "Beni Mellal"
        }
      },
      {
        "location": {
          "name": "Berrechid"
        }
      },
      {
        "location": {
          "name": "Casablanca"
        }
      },
      {
        "location": {
          "name": "Deroua"
        }
      },
      {
        "location": {
          "name": "El Gara"
        }
      },
      {
        "location": {
          "name": "El Hajeb"
        }
      },
      {
        "location": {
          "name": "El Jadida"
        }
      },
      {
        "location": {
          "name": "Erfoud"
        }
      },
      {
        "location": {
          "name": "Fes"
        }
      },
      {
        "location": {
          "name": "Fkih Ben Salah"
        }
      },
      {
        "location": {
          "name": "Kenitra"
        }
      },
      {
        "location": {
          "name": "Khemisset"
        }
      },
      {
        "location": {
          "name": "Khouribga"
        }
      },
      {
        "location": {
          "name": "Ksar el Kebir"
        }
      },
      {
        "location": {
          "name": "Larache"
        }
      },
      {
        "location": {
          "name": "Mansour"
        }
      },
      {
        "location": {
          "name": "Marrakesh"
        }
      },
      {
        "location": {
          "name": "Mehediyah"
        }
      },
      {
        "location": {
          "name": "Meknes"
        }
      },
      {
        "location": {
          "name": "Mohammedia"
        }
      },
      {
        "location": {
          "name": "Nador"
        }
      },
      {
        "location": {
          "name": "Ouazzane"
        }
      },
      {
        "location": {
          "name": "Oued Zem"
        }
      },
      {
        "location": {
          "name": "Oujda"
        }
      },
      {
        "location": {
          "name": "Oulad Teima"
        }
      },
      {
        "location": {
          "name": "Rabat"
        }
      },
      {
        "location": {
          "name": "Safi"
        }
      },
      {
        "location": {
          "name": "Sefrou"
        }
      },
      {
        "location": {
          "name": "Settat"
        }
      },
      {
        "location": {
          "name": "Sidi Bennour"
        }
      },
      {
        "location": {
          "name": "Sidi Slimane"
        }
      },
      {
        "location": {
          "name": "Skhirat"
        }
      },
      {
        "location": {
          "name": "Tahala"
        }
      },
      {
        "location": {
          "name": "Tan-Tan"
        }
      },
      {
        "location": {
          "name": "Tangier"
        }
      },
      {
        "location": {
          "name": "Tarfaya"
        }
      },
      {
        "location": {
          "name": "Taza"
        }
      },
      {
        "location": {
          "name": "Temara"
        }
      },
      {
        "location": {
          "name": "Tiflet"
        }
      },
      {
        "location": {
          "name": "Tiznit"
        }
      },
      {
        "location": {
          "name": "Touissite"
        }
      }
    ]
  },
  {
    "location": {
      "name": "Mozambique"
    },
    "children": [
      {
        "location": {
          "name": "Beira"
        }
      },
      {
        "location": {
          "name": "Maputo"
        }
      },
      {
        "location": {
          "name": "Matola"
        }
      },
      {
        "location": {
          "name": "Mozambique"
        }
      },
      {
        "location": {
          "name": "Nampula"
        }
      },
      {
        "location": {
          "name": "Pemba"
        }
      },
      {
        "location": {
          "name": "Quelimane"
        }
      },
      {
        "location": {
          "name": "Tete"
        }
      }
    ]
  },
  {
    "location": {
      "name": "Nigeria"
    },
    "children": [
      {
        "location": {
          "name": "Aba"
        }
      },
      {
        "location": {
          "name": "Abakaliki"
        }
      },
      {
        "location": {
          "name": "Abeokuta"
        }
      },
      {
        "location": {
          "name": "Abraka"
        }
      },
      {
        "location": {
          "name": "Abraka"
        }
      },
      {
        "location": {
          "name": "Abuja"
        }
      },
      {
        "location": {
          "name": "Ado-Ekiti"
        }
      },
      {
        "location": {
          "name": "Adodo"
        }
      },
      {
        "location": {
          "name": "Aganga"
        }
      },
      {
        "location": {
          "name": "Agege"
        }
      },
      {
        "location": {
          "name": "Agidingbi"
        }
      },
      {
        "location": {
          "name": "Ajegunle"
        }
      },
      {
        "location": {
          "name": "Ajuwon"
        }
      },
      {
        "location": {
          "name": "Akure"
        }
      },
      {
        "location": {
          "name": "Alimosho"
        }
      },
      {
        "location": {
          "name": "Anambra"
        }
      },
      {
        "location": {
          "name": "Apapa"
        }
      },
      {
        "location": {
          "name": "Ayobo"
        }
      },
      {
        "location": {
          "name": "Benin City"
        }
      },
      {
        "location": {
          "name": "Birnin Kebbi"
        }
      },
      {
        "location": {
          "name": "Bonny"
        }
      },
      {
        "location": {
          "name": "Burutu"
        }
      },
      {
        "location": {
          "name": "Bwari"
        }
      },
      {
        "location": {
          "name": "Calabar"
        }
      },
      {
        "location": {
          "name": "Chafe"
        }
      },
      {
        "location": {
          "name": "Damaturu"
        }
      },
      {
        "location": {
          "name": "Egbeda"
        }
      },
      {
        "location": {
          "name": "Ekpoma"
        }
      },
      {
        "location": {
          "name": "Enugu"
        }
      },
      {
        "location": {
          "name": "Forum"
        }
      },
      {
        "location": {
          "name": "Funtua"
        }
      },
      {
        "location": {
          "name": "Ibadan"
        }
      },
      {
        "location": {
          "name": "Ido"
        }
      },
      {
        "location": {
          "name": "Ifako"
        }
      },
      {
        "location": {
          "name": "Igando"
        }
      },
      {
        "location": {
          "name": "Igueben"
        }
      },
      {
        "location": {
          "name": "Ikeja"
        }
      },
      {
        "location": {
          "name": "Ikorodu"
        }
      },
      {
        "location": {
          "name": "Ikotun"
        }
      },
      {
        "location": {
          "name": "Ile-Ife"
        }
      },
      {
        "location": {
          "name": "Ilesa"
        }
      },
      {
        "location": {
          "name": "Ilorin"
        }
      },
      {
        "location": {
          "name": "Ipaja"
        }
      },
      {
        "location": {
          "name": "Iseri-Oke"
        }
      },
      {
        "location": {
          "name": "Isolo"
        }
      },
      {
        "location": {
          "name": "Jalingo"
        }
      },
      {
        "location": {
          "name": "Jos"
        }
      },
      {
        "location": {
          "name": "Kaduna"
        }
      },
      {
        "location": {
          "name": "Kano"
        }
      },
      {
        "location": {
          "name": "Kebbi"
        }
      },
      {
        "location": {
          "name": "Lagos"
        }
      },
      {
        "location": {
          "name": "Lekki"
        }
      },
      {
        "location": {
          "name": "Lokoja"
        }
      },
      {
        "location": {
          "name": "Magodo"
        }
      },
      {
        "location": {
          "name": "Makurdi"
        }
      },
      {
        "location": {
          "name": "Maryland"
        }
      },
      {
        "location": {
          "name": "Minna"
        }
      },
      {
        "location": {
          "name": "Mogho"
        }
      },
      {
        "location": {
          "name": "Mowe"
        }
      },
      {
        "location": {
          "name": "Mushin"
        }
      },
      {
        "location": {
          "name": "Nsukka"
        }
      },
      {
        "location": {
          "name": "Obafemi"
        }
      },
      {
        "location": {
          "name": "Obudu"
        }
      },
      {
        "location": {
          "name": "Odau"
        }
      },
      {
        "location": {
          "name": "Ojo"
        }
      },
      {
        "location": {
          "name": "Ojota"
        }
      },
      {
        "location": {
          "name": "Ondo"
        }
      },
      {
        "location": {
          "name": "Onigbongbo"
        }
      },
      {
        "location": {
          "name": "Orile Oshodi"
        }
      },
      {
        "location": {
          "name": "Oshodi"
        }
      },
      {
        "location": {
          "name": "Osogbo"
        }
      },
      {
        "location": {
          "name": "Ota"
        }
      },
      {
        "location": {
          "name": "Owerri"
        }
      },
      {
        "location": {
          "name": "Oworonsoki"
        }
      },
      {
        "location": {
          "name": "Port Harcourt"
        }
      },
      {
        "location": {
          "name": "Shomolu"
        }
      },
      {
        "location": {
          "name": "Suleja"
        }
      },
      {
        "location": {
          "name": "Suru-Lere"
        }
      },
      {
        "location": {
          "name": "Tara"
        }
      },
      {
        "location": {
          "name": "Ughelli"
        }
      },
      {
        "location": {
          "name": "Ungwan Madaki"
        }
      },
      {
        "location": {
          "name": "Uyo"
        }
      },
      {
        "location": {
          "name": "Warri"
        }
      },
      {
        "location": {
          "name": "Warri"
        }
      },
      {
        "location": {
          "name": "Yaba"
        }
      },
      {
        "location": {
          "name": "Yola"
        }
      },
      {
        "location": {
          "name": "Zaria"
        }
      }
    ]
  },
  {
    "location": {
      "name": "Senegal"
    },
    "children": [
      {
        "location": {
          "name": "Boussinki"
        }
      },
      {
        "location": {
          "name": "Camberene"
        }
      },
      {
        "location": {
          "name": "Dakar"
        }
      },
      {
        "location": {
          "name": "Dodji"
        }
      },
      {
        "location": {
          "name": "Guediawaye"
        }
      },
      {
        "location": {
          "name": "Kaolack"
        }
      },
      {
        "location": {
          "name": "Kedougou"
        }
      },
      {
        "location": {
          "name": "Louga"
        }
      },
      {
        "location": {
          "name": "Madina Kokoun"
        }
      },
      {
        "location": {
          "name": "Saint-Louis"
        }
      },
      {
        "location": {
          "name": "Sama"
        }
      },
      {
        "location": {
          "name": "Tanaf"
        }
      }
    ]
  },
  {
    "location": {
      "name": "South Africa"
    },
    "children": [
      {
        "location": {
          "name": "Alberton"
        }
      },
      {
        "location": {
          "name": "Alice"
        }
      },
      {
        "location": {
          "name": "Alrode"
        }
      },
      {
        "location": {
          "name": "Amanzimtoti"
        }
      },
      {
        "location": {
          "name": "Ashton"
        }
      },
      {
        "location": {
          "name": "Atlantis"
        }
      },
      {
        "location": {
          "name": "Balfour"
        }
      },
      {
        "location": {
          "name": "Bathurst"
        }
      },
      {
        "location": {
          "name": "Beaufort West"
        }
      },
      {
        "location": {
          "name": "Bedfordview"
        }
      },
      {
        "location": {
          "name": "Belhar"
        }
      },
      {
        "location": {
          "name": "Bellville"
        }
      },
      {
        "location": {
          "name": "Benoni"
        }
      },
      {
        "location": {
          "name": "Bergvliet"
        }
      },
      {
        "location": {
          "name": "Bethal"
        }
      },
      {
        "location": {
          "name": "Bethlehem"
        }
      },
      {
        "location": {
          "name": "Bloemfontein"
        }
      },
      {
        "location": {
          "name": "Boksburg"
        }
      },
      {
        "location": {
          "name": "Bothasig"
        }
      },
      {
        "location": {
          "name": "Botshabelo"
        }
      },
      {
        "location": {
          "name": "Braamfontein"
        }
      },
      {
        "location": {
          "name": "Brackenfell"
        }
      },
      {
        "location": {
          "name": "Brakpan"
        }
      },
      {
        "location": {
          "name": "Bredasdorp"
        }
      },
      {
        "location": {
          "name": "Brits"
        }
      },
      {
        "location": {
          "name": "Bronkhorstspruit"
        }
      },
      {
        "location": {
          "name": "Brooklyn"
        }
      },
      {
        "location": {
          "name": "Bryanston"
        }
      },
      {
        "location": {
          "name": "Buffalo"
        }
      },
      {
        "location": {
          "name": "Butterworth"
        }
      },
      {
        "location": {
          "name": "Cape Town"
        }
      },
      {
        "location": {
          "name": "Capital Park"
        }
      },
      {
        "location": {
          "name": "Carletonville"
        }
      },
      {
        "location": {
          "name": "Carolina"
        }
      },
      {
        "location": {
          "name": "Centurion"
        }
      },
      {
        "location": {
          "name": "City of Cape Town"
        }
      },
      {
        "location": {
          "name": "Clanwilliam"
        }
      },
      {
        "location": {
          "name": "Claremont"
        }
      },
      {
        "location": {
          "name": "Coega"
        }
      },
      {
        "location": {
          "name": "Coligny"
        }
      },
      {
        "location": {
          "name": "Constantia"
        }
      },
      {
        "location": {
          "name": "Craighall"
        }
      },
      {
        "location": {
          "name": "Cullinan"
        }
      },
      {
        "location": {
          "name": "De Aar"
        }
      },
      {
        "location": {
          "name": "Delmas"
        }
      },
      {
        "location": {
          "name": "Deneysville"
        }
      },
      {
        "location": {
          "name": "Despatch"
        }
      },
      {
        "location": {
          "name": "Doornfontein"
        }
      },
      {
        "location": {
          "name": "Dube Location"
        }
      },
      {
        "location": {
          "name": "Duiwelskloof"
        }
      },
      {
        "location": {
          "name": "Dullstroom"
        }
      },
      {
        "location": {
          "name": "Dundee"
        }
      },
      {
        "location": {
          "name": "Durban"
        }
      },
      {
        "location": {
          "name": "Durbanville"
        }
      },
      {
        "location": {
          "name": "East London"
        }
      },
      {
        "location": {
          "name": "Edenburg"
        }
      },
      {
        "location": {
          "name": "Edenvale"
        }
      },
      {
        "location": {
          "name": "Eersterivier"
        }
      },
      {
        "location": {
          "name": "Elandsfontein"
        }
      },
      {
        "location": {
          "name": "Elarduspark"
        }
      },
      {
        "location": {
          "name": "Eloff"
        }
      },
      {
        "location": {
          "name": "Elsburg"
        }
      },
      {
        "location": {
          "name": "Elsenburg"
        }
      },
      {
        "location": {
          "name": "Emerald Hill"
        }
      },
      {
        "location": {
          "name": "Emnambithi-Ladysmith"
        }
      },
      {
        "location": {
          "name": "Empangeni"
        }
      },
      {
        "location": {
          "name": "Erasmia"
        }
      },
      {
        "location": {
          "name": "Ermelo"
        }
      },
      {
        "location": {
          "name": "Eshowe"
        }
      },
      {
        "location": {
          "name": "Evander"
        }
      },
      {
        "location": {
          "name": "Faure"
        }
      },
      {
        "location": {
          "name": "Florida Glen"
        }
      },
      {
        "location": {
          "name": "Fochville"
        }
      },
      {
        "location": {
          "name": "Fordsburg"
        }
      },
      {
        "location": {
          "name": "Fort Cox"
        }
      },
      {
        "location": {
          "name": "Franschhoek"
        }
      },
      {
        "location": {
          "name": "Gansbaai"
        }
      },
      {
        "location": {
          "name": "Ganspan"
        }
      },
      {
        "location": {
          "name": "George"
        }
      },
      {
        "location": {
          "name": "Germiston"
        }
      },
      {
        "location": {
          "name": "Gezina"
        }
      },
      {
        "location": {
          "name": "Gillitts"
        }
      },
      {
        "location": {
          "name": "Gingindlovu"
        }
      },
      {
        "location": {
          "name": "Glen Austin"
        }
      },
      {
        "location": {
          "name": "Goodwood"
        }
      },
      {
        "location": {
          "name": "Graaff Reinet"
        }
      },
      {
        "location": {
          "name": "Grabouw"
        }
      },
      {
        "location": {
          "name": "Grahamstown"
        }
      },
      {
        "location": {
          "name": "Greytown"
        }
      },
      {
        "location": {
          "name": "Groblersdal"
        }
      },
      {
        "location": {
          "name": "Haenertsburg"
        }
      },
      {
        "location": {
          "name": "Harrismith"
        }
      },
      {
        "location": {
          "name": "Hartbeespoort"
        }
      },
      {
        "location": {
          "name": "Hartenbos"
        }
      },
      {
        "location": {
          "name": "Hartswater"
        }
      },
      {
        "location": {
          "name": "Hatfield"
        }
      },
      {
        "location": {
          "name": "Hawston"
        }
      },
      {
        "location": {
          "name": "Hazyview"
        }
      },
      {
        "location": {
          "name": "Heidelberg"
        }
      },
      {
        "location": {
          "name": "Hekpoort"
        }
      },
      {
        "location": {
          "name": "Henley on Klip"
        }
      },
      {
        "location": {
          "name": "Hennenman"
        }
      },
      {
        "location": {
          "name": "Hermanus"
        }
      },
      {
        "location": {
          "name": "Hillcrest"
        }
      },
      {
        "location": {
          "name": "Hilton"
        }
      },
      {
        "location": {
          "name": "Himeville"
        }
      },
      {
        "location": {
          "name": "Hluhluwe"
        }
      },
      {
        "location": {
          "name": "Hoedspruit"
        }
      },
      {
        "location": {
          "name": "Hogsback"
        }
      },
      {
        "location": {
          "name": "Houghton Estate"
        }
      },
      {
        "location": {
          "name": "Hout Bay"
        }
      },
      {
        "location": {
          "name": "Howick"
        }
      },
      {
        "location": {
          "name": "Humansdorp"
        }
      },
      {
        "location": {
          "name": "Hyde Park"
        }
      },
      {
        "location": {
          "name": "Irene"
        }
      },
      {
        "location": {
          "name": "Isando"
        }
      },
      {
        "location": {
          "name": "Ixopo"
        }
      },
      {
        "location": {
          "name": "Johannesburg"
        }
      },
      {
        "location": {
          "name": "Kalkbaai"
        }
      },
      {
        "location": {
          "name": "Katlehong"
        }
      },
      {
        "location": {
          "name": "Kempton Park"
        }
      },
      {
        "location": {
          "name": "Kimberley"
        }
      },
      {
        "location": {
          "name": "Kingsborough"
        }
      },
      {
        "location": {
          "name": "Kingsley"
        }
      },
      {
        "location": {
          "name": "Kingsmead"
        }
      },
      {
        "location": {
          "name": "Kinross"
        }
      },
      {
        "location": {
          "name": "Kleinmond"
        }
      },
      {
        "location": {
          "name": "Klerksdorp"
        }
      },
      {
        "location": {
          "name": "Kloof"
        }
      },
      {
        "location": {
          "name": "Knysna"
        }
      },
      {
        "location": {
          "name": "Kokstad"
        }
      },
      {
        "location": {
          "name": "Kraaifontein"
        }
      },
      {
        "location": {
          "name": "Kranskop"
        }
      },
      {
        "location": {
          "name": "Kriel"
        }
      },
      {
        "location": {
          "name": "Kroonstad"
        }
      },
      {
        "location": {
          "name": "Krugersdorp"
        }
      },
      {
        "location": {
          "name": "Kuils River"
        }
      },
      {
        "location": {
          "name": "KwaDukuza"
        }
      },
      {
        "location": {
          "name": "La Lucia"
        }
      },
      {
        "location": {
          "name": "La Motte"
        }
      },
      {
        "location": {
          "name": "Ladybrand"
        }
      },
      {
        "location": {
          "name": "Lansdowne"
        }
      },
      {
        "location": {
          "name": "Laudium"
        }
      },
      {
        "location": {
          "name": "Lephalale"
        }
      },
      {
        "location": {
          "name": "Lichtenburg"
        }
      },
      {
        "location": {
          "name": "Lombardy East"
        }
      },
      {
        "location": {
          "name": "London"
        }
      },
      {
        "location": {
          "name": "Louis Trichardt"
        }
      },
      {
        "location": {
          "name": "Lutzville"
        }
      },
      {
        "location": {
          "name": "Lydenburg"
        }
      },
      {
        "location": {
          "name": "Lyndhurst"
        }
      },
      {
        "location": {
          "name": "Lynnwood"
        }
      },
      {
        "location": {
          "name": "Lyttelton"
        }
      },
      {
        "location": {
          "name": "Machadodorp"
        }
      },
      {
        "location": {
          "name": "Mafikeng"
        }
      },
      {
        "location": {
          "name": "Maidstone"
        }
      },
      {
        "location": {
          "name": "Majuba"
        }
      },
      {
        "location": {
          "name": "Malmesbury"
        }
      },
      {
        "location": {
          "name": "Malvern"
        }
      },
      {
        "location": {
          "name": "Maraisburg"
        }
      },
      {
        "location": {
          "name": "Margate"
        }
      },
      {
        "location": {
          "name": "Marshalltown"
        }
      },
      {
        "location": {
          "name": "Meadowridge"
        }
      },
      {
        "location": {
          "name": "Medunsa"
        }
      },
      {
        "location": {
          "name": "Melkbosstrand"
        }
      },
      {
        "location": {
          "name": "Merrivale"
        }
      },
      {
        "location": {
          "name": "Messina"
        }
      },
      {
        "location": {
          "name": "Meyerton"
        }
      },
      {
        "location": {
          "name": "Middelburg"
        }
      },
      {
        "location": {
          "name": "Middelburg"
        }
      },
      {
        "location": {
          "name": "Midrand"
        }
      },
      {
        "location": {
          "name": "Milnerton"
        }
      },
      {
        "location": {
          "name": "Mmabatho"
        }
      },
      {
        "location": {
          "name": "Mobeni"
        }
      },
      {
        "location": {
          "name": "Modderfontein"
        }
      },
      {
        "location": {
          "name": "Mokopane"
        }
      },
      {
        "location": {
          "name": "Montagu"
        }
      },
      {
        "location": {
          "name": "Monument Park"
        }
      },
      {
        "location": {
          "name": "Mooi River"
        }
      },
      {
        "location": {
          "name": "Mookgophong"
        }
      },
      {
        "location": {
          "name": "Moorreesburg"
        }
      },
      {
        "location": {
          "name": "Morningside Manor"
        }
      },
      {
        "location": {
          "name": "Mossel Bay"
        }
      },
      {
        "location": {
          "name": "Mount Edgecombe"
        }
      },
      {
        "location": {
          "name": "Mthatha"
        }
      },
      {
        "location": {
          "name": "Muizenberg"
        }
      },
      {
        "location": {
          "name": "Napier"
        }
      },
      {
        "location": {
          "name": "Nelspruit"
        }
      },
      {
        "location": {
          "name": "New Germany"
        }
      },
      {
        "location": {
          "name": "Newcastle"
        }
      },
      {
        "location": {
          "name": "Newlands"
        }
      },
      {
        "location": {
          "name": "Nigel"
        }
      },
      {
        "location": {
          "name": "Northcliff"
        }
      },
      {
        "location": {
          "name": "Odendaalsrus"
        }
      },
      {
        "location": {
          "name": "Ogies"
        }
      },
      {
        "location": {
          "name": "Olifantsfontein"
        }
      },
      {
        "location": {
          "name": "Onderstepoort"
        }
      },
      {
        "location": {
          "name": "Onverwacht"
        }
      },
      {
        "location": {
          "name": "Oranjeville"
        }
      },
      {
        "location": {
          "name": "Oranjezicht"
        }
      },
      {
        "location": {
          "name": "Ottosdal"
        }
      },
      {
        "location": {
          "name": "Oudtshoorn"
        }
      },
      {
        "location": {
          "name": "Overport"
        }
      },
      {
        "location": {
          "name": "Paarl"
        }
      },
      {
        "location": {
          "name": "Panorama"
        }
      },
      {
        "location": {
          "name": "Parktown"
        }
      },
      {
        "location": {
          "name": "Parkview"
        }
      },
      {
        "location": {
          "name": "Parow"
        }
      },
      {
        "location": {
          "name": "Peninsula"
        }
      },
      {
        "location": {
          "name": "Phalaborwa"
        }
      },
      {
        "location": {
          "name": "Philadelphia"
        }
      },
      {
        "location": {
          "name": "Philipstown"
        }
      },
      {
        "location": {
          "name": "Phoenix"
        }
      },
      {
        "location": {
          "name": "Phokeng"
        }
      },
      {
        "location": {
          "name": "Pietermaritzburg"
        }
      },
      {
        "location": {
          "name": "Pinelands"
        }
      },
      {
        "location": {
          "name": "Pinetown"
        }
      },
      {
        "location": {
          "name": "Plettenberg Bay"
        }
      },
      {
        "location": {
          "name": "Plumstead"
        }
      },
      {
        "location": {
          "name": "Polokwane"
        }
      },
      {
        "location": {
          "name": "Pongola"
        }
      },
      {
        "location": {
          "name": "Port Alfred"
        }
      },
      {
        "location": {
          "name": "Port Elizabeth"
        }
      },
      {
        "location": {
          "name": "Port Shepstone"
        }
      },
      {
        "location": {
          "name": "Potchefstroom"
        }
      },
      {
        "location": {
          "name": "Pretoria"
        }
      },
      {
        "location": {
          "name": "Prieska"
        }
      },
      {
        "location": {
          "name": "Primrose"
        }
      },
      {
        "location": {
          "name": "Pringle Bay"
        }
      },
      {
        "location": {
          "name": "Queensburgh"
        }
      },
      {
        "location": {
          "name": "Queenstown"
        }
      },
      {
        "location": {
          "name": "Queenswood"
        }
      },
      {
        "location": {
          "name": "Randburg"
        }
      },
      {
        "location": {
          "name": "Randfontein"
        }
      },
      {
        "location": {
          "name": "Rawsonville"
        }
      },
      {
        "location": {
          "name": "Rhodes"
        }
      },
      {
        "location": {
          "name": "Richards Bay"
        }
      },
      {
        "location": {
          "name": "Richmond"
        }
      },
      {
        "location": {
          "name": "Riebeek-Kasteel"
        }
      },
      {
        "location": {
          "name": "Rivonia"
        }
      },
      {
        "location": {
          "name": "Roggebaai"
        }
      },
      {
        "location": {
          "name": "Roodepoort"
        }
      },
      {
        "location": {
          "name": "Rooigrond"
        }
      },
      {
        "location": {
          "name": "Rooihuiskraal"
        }
      },
      {
        "location": {
          "name": "Rosebank"
        }
      },
      {
        "location": {
          "name": "Rosettenville"
        }
      },
      {
        "location": {
          "name": "Rosslyn"
        }
      },
      {
        "location": {
          "name": "Rustenburg"
        }
      },
      {
        "location": {
          "name": "Sabie"
        }
      },
      {
        "location": {
          "name": "Saint Helena Bay"
        }
      },
      {
        "location": {
          "name": "Saint James"
        }
      },
      {
        "location": {
          "name": "Saldanha"
        }
      },
      {
        "location": {
          "name": "Salt Rock"
        }
      },
      {
        "location": {
          "name": "Sandown"
        }
      },
      {
        "location": {
          "name": "Sandton"
        }
      },
      {
        "location": {
          "name": "Sasolburg"
        }
      },
      {
        "location": {
          "name": "Schweizer-Reneke"
        }
      },
      {
        "location": {
          "name": "Scottburgh"
        }
      },
      {
        "location": {
          "name": "Sebokeng"
        }
      },
      {
        "location": {
          "name": "Secunda"
        }
      },
      {
        "location": {
          "name": "Sedgefield"
        }
      },
      {
        "location": {
          "name": "Senekal"
        }
      },
      {
        "location": {
          "name": "Shelly Beach"
        }
      },
      {
        "location": {
          "name": "Silverton"
        }
      },
      {
        "location": {
          "name": "Sinoville"
        }
      },
      {
        "location": {
          "name": "Somerset West"
        }
      },
      {
        "location": {
          "name": "Soshanguve"
        }
      },
      {
        "location": {
          "name": "Soweto"
        }
      },
      {
        "location": {
          "name": "Springs"
        }
      },
      {
        "location": {
          "name": "Standerton"
        }
      },
      {
        "location": {
          "name": "Stanford"
        }
      },
      {
        "location": {
          "name": "Stellenbosch"
        }
      },
      {
        "location": {
          "name": "Stilfontein"
        }
      },
      {
        "location": {
          "name": "Strand"
        }
      },
      {
        "location": {
          "name": "Sun Valley"
        }
      },
      {
        "location": {
          "name": "Swartkops"
        }
      },
      {
        "location": {
          "name": "Temba"
        }
      },
      {
        "location": {
          "name": "Tembisa"
        }
      },
      {
        "location": {
          "name": "Thabazimbi"
        }
      },
      {
        "location": {
          "name": "The Rest"
        }
      },
      {
        "location": {
          "name": "Thohoyandou"
        }
      },
      {
        "location": {
          "name": "Three Anchor Bay"
        }
      },
      {
        "location": {
          "name": "Three Rivers"
        }
      },
      {
        "location": {
          "name": "Tokai"
        }
      },
      {
        "location": {
          "name": "Tongaat"
        }
      },
      {
        "location": {
          "name": "Tzaneen"
        }
      },
      {
        "location": {
          "name": "Uitenhage"
        }
      },
      {
        "location": {
          "name": "Umbogintwini"
        }
      },
      {
        "location": {
          "name": "Umdloti"
        }
      },
      {
        "location": {
          "name": "Umhlanga"
        }
      },
      {
        "location": {
          "name": "Umkomaas"
        }
      },
      {
        "location": {
          "name": "Umtentweni"
        }
      },
      {
        "location": {
          "name": "Upington"
        }
      },
      {
        "location": {
          "name": "Vaalbank"
        }
      },
      {
        "location": {
          "name": "Vaalpark"
        }
      },
      {
        "location": {
          "name": "Vanderbijlpark"
        }
      },
      {
        "location": {
          "name": "Vereeniging"
        }
      },
      {
        "location": {
          "name": "Verulam"
        }
      },
      {
        "location": {
          "name": "Villiersdorp"
        }
      },
      {
        "location": {
          "name": "Virginia"
        }
      },
      {
        "location": {
          "name": "Vosloorus"
        }
      },
      {
        "location": {
          "name": "Vrededorp"
        }
      },
      {
        "location": {
          "name": "Vredenburg"
        }
      },
      {
        "location": {
          "name": "Vryheid"
        }
      },
      {
        "location": {
          "name": "Walkerville"
        }
      },
      {
        "location": {
          "name": "Walmer Heights"
        }
      },
      {
        "location": {
          "name": "Warner Beach"
        }
      },
      {
        "location": {
          "name": "Wartburg"
        }
      },
      {
        "location": {
          "name": "Waverley"
        }
      },
      {
        "location": {
          "name": "Waverley"
        }
      },
      {
        "location": {
          "name": "Welgelegen"
        }
      },
      {
        "location": {
          "name": "Welgemoed"
        }
      },
      {
        "location": {
          "name": "Welkom"
        }
      },
      {
        "location": {
          "name": "Welkom"
        }
      },
      {
        "location": {
          "name": "Wellington"
        }
      },
      {
        "location": {
          "name": "Weltevreden"
        }
      },
      {
        "location": {
          "name": "Weltevreedenpark"
        }
      },
      {
        "location": {
          "name": "Westonaria"
        }
      },
      {
        "location": {
          "name": "Westville"
        }
      },
      {
        "location": {
          "name": "White River"
        }
      },
      {
        "location": {
          "name": "Wilderness"
        }
      },
      {
        "location": {
          "name": "Winterton"
        }
      },
      {
        "location": {
          "name": "Witbank"
        }
      },
      {
        "location": {
          "name": "Witpoortjie"
        }
      },
      {
        "location": {
          "name": "Wonderboom"
        }
      },
      {
        "location": {
          "name": "Worcester"
        }
      },
      {
        "location": {
          "name": "Wynberg"
        }
      },
      {
        "location": {
          "name": "Zeerust"
        }
      }
    ]
  },
  {
    "location": {
      "name": "Sudan"
    },
    "children": [
      {
        "location": {
          "name": "Kassala"
        }
      },
      {
        "location": {
          "name": "Khartoum"
        }
      },
      {
        "location": {
          "name": "Nyala"
        }
      },
      {
        "location": {
          "name": "Shendi"
        }
      },
      {
        "location": {
          "name": "Thabit"
        }
      },
      {
        "location": {
          "name": "Umm Durman"
        }
      }
    ]
  },
  {
    "location": {
      "name": "Tanzania"
    },
    "children": [
      {
        "location": {
          "name": "Arusha"
        }
      },
      {
        "location": {
          "name": "Bukoba"
        }
      },
      {
        "location": {
          "name": "Dar es Salaam"
        }
      },
      {
        "location": {
          "name": "Dodoma"
        }
      },
      {
        "location": {
          "name": "Morogoro"
        }
      },
      {
        "location": {
          "name": "Mwanza"
        }
      },
      {
        "location": {
          "name": "Njombe"
        }
      },
      {
        "location": {
          "name": "Raha"
        }
      },
      {
        "location": {
          "name": "Tanga"
        }
      },
      {
        "location": {
          "name": "Zanzibar"
        }
      }
    ]
  },
  {
    "location": {
      "name": "Zambia"
    },
    "children": [
      {
        "location": {
          "name": "Kalomo"
        }
      },
      {
        "location": {
          "name": "Kitwe"
        }
      },
      {
        "location": {
          "name": "Livingstone"
        }
      },
      {
        "location": {
          "name": "Lusaka"
        }
      },
      {
        "location": {
          "name": "Macha"
        }
      },
      {
        "location": {
          "name": "Mumbwa"
        }
      },
      {
        "location": {
          "name": "Ndola"
        }
      },
      {
        "location": {
          "name": "Siavonga"
        }
      },
      {
        "location": {
          "name": "Solwezi"
        }
      }
    ]
  },
  {
    "location": {
      "name": "Zimbabwe"
    },
    "children": [
      {
        "location": {
          "name": "Bulawayo"
        }
      },
      {
        "location": {
          "name": "Chinhoyi"
        }
      },
      {
        "location": {
          "name": "Greendale"
        }
      },
      {
        "location": {
          "name": "Gwanda"
        }
      },
      {
        "location": {
          "name": "Harare"
        }
      },
      {
        "location": {
          "name": "Kwekwe"
        }
      },
      {
        "location": {
          "name": "Mufakose"
        }
      },
      {
        "location": {
          "name": "Mutare"
        }
      },
      {
        "location": {
          "name": "Victoria Falls"
        }
      }
    ]
  }
]
